BMSS/__init__.py
BMSS/aicanalysis.py
BMSS/curvefitting.py
BMSS/icanalysis.py
BMSS/mcmc.py
BMSS/read_data.py
BMSS/scipy_wrappers.py
BMSS/sensitivityanalysis.py
BMSS/simulation.py
BMSS/strike_goldd_simplified.py
BMSS/traceanalysis.py
BMSS/models/MBase.db
BMSS/models/UBase.db
BMSS/models/__init__.py
BMSS/models/_backend_reset.py
BMSS/models/checker_do_not_run.py
BMSS/models/database_settings.ini
BMSS/models/ia_model_import.py
BMSS/models/ia_results.py
BMSS/models/model_checker.py
BMSS/models/model_coder.py
BMSS/models/model_handler.py
BMSS/models/settings_checker.py
BMSS/models/settings_checker_backup.py
BMSS/models/settings_handler.py
BMSS/models/settings_handler_backup.py
BMSS/models/setup_cf.py
BMSS/models/setup_sen.py
BMSS/models/setup_sg.py
BMSS/models/setup_sim.py
BMSS/models/utils_settings.py
BMSS/models/BMSS_markup/TestModel_Dummy.ini
BMSS/models/BMSS_markup/TestModel_Dummy_CellModel_CellularResources_ProteomeAllocation_RibosomeLimitation_2.ini
BMSS/models/BMSS_markup/TestModel_LogicGate_ORgate_DelayActivation.ini
BMSS/models/BMSS_markup/TestModel_Logistic_Inducible.ini
BMSS/models/BMSS_markup/TestModel_Monod_Constitutive_Double.ini
BMSS/models/BMSS_markup/TestModel_Monod_Constitutive_Single.ini
BMSS/models/BMSS_markup/TestModel_Monod_Constitutive_Single_ProductInhibition.ini
BMSS/models/BMSS_markup/TestModel_Monod_Inducible.ini
BMSS/models/BMSS_markup/TestModel_Monod_Inducible_Bioconversion_ProductInhibitedGrowth.ini
BMSS/models/BMSS_markup/TestModel_Naringenin_RBSStrength_PromoterStrength.ini
BMSS/models/BMSS_markup/bmss01.ini
BMSS/models/BMSS_markup/bmss02.ini
BMSS/models/BMSS_markup/bmss03.ini
BMSS/models/BMSS_markup/bmss04.ini
BMSS/models/BMSS_markup/bmss05.ini
BMSS/models/BMSS_markup/bmss06.ini
BMSS/models/BMSS_markup/bmss07.ini
BMSS/models/BMSS_markup/bmss08.ini
BMSS/models/BMSS_markup/bmss09.ini
BMSS/models/BMSS_markup/bmss10.ini
BMSS/models/BMSS_markup/bmss11.ini
BMSS/models/BMSS_markup/bmss12.ini
BMSS/models/BMSS_markup/bmss13.ini
BMSS-2.0.17.dist-info/LICENSE.rst
BMSS-2.0.17.dist-info/METADATA
BMSS-2.0.17.dist-info/WHEEL
BMSS-2.0.17.dist-info/top_level.txt
BMSS-2.0.17.dist-info/RECORD
