Metadata-Version: 2.1
Name: BMSS
Version: 2.0.17
Summary: A package for dyanmic model analysis.
Home-page: https://github.com/EngBioNUS/BMSS2
Author: Russell Ngo
Author-email: biernjk@nus.edu.sg
License: UNKNOWN
Platform: UNKNOWN
Classifier: Intended Audience :: Developers
Classifier: Intended Audience :: Science/Research
Classifier: License :: OSI Approved :: MIT License
Classifier: Operating System :: OS Independent
Requires-Python: >=3.7
Requires-Dist: numpy
Requires-Dist: scipy
Requires-Dist: numba
Requires-Dist: matplotlib
Requires-Dist: pandas
Requires-Dist: PyYAML
Requires-Dist: SALib
Requires-Dist: arviz
Requires-Dist: xarray
